twitch_dota_extension/lib.py
twitch_dota_extension/pgl.py
twitch_dota_extension/tooltips.py
twitch_dota_extension-0.1.14.dist-info/METADATA
twitch_dota_extension-0.1.14.dist-info/WHEEL
twitch_dota_extension-0.1.14.dist-info/RECORD
